orbited-debug.cfg
orbited.cfg
setup.py
start.py
orbited/__init__.py
orbited/cometsession.py
orbited/config.py
orbited/json.py
orbited/logging.py
orbited/proxy.py
orbited/start.py
orbited/util.py
orbited.egg-info/PKG-INFO
orbited.egg-info/SOURCES.txt
orbited.egg-info/dependency_links.txt
orbited.egg-info/entry_points.txt
orbited.egg-info/not-zip-safe
orbited.egg-info/requires.txt
orbited.egg-info/top_level.txt
orbited/servers/__init__.py
orbited/servers/announce.py
orbited/servers/echo.py
orbited/servers/lineecho.py
orbited/servers/monitor.py
orbited/servers/rude.py
orbited/static/HTMLFileClose.js
orbited/static/HTMLFileFrame.js
orbited/static/JSON.js
orbited/static/Orbited.js
orbited/static/log4js.js
orbited/static/test_csp.html
orbited/static/test_socket.html
orbited/static/xsdClose.html
orbited/static/xsdrBridge.html
orbited/static/demos/index.html
orbited/static/demos/chat/chat.css
orbited/static/demos/chat/chat.js
orbited/static/demos/chat/index.html
orbited/static/demos/dispatch/index.html
orbited/static/demos/lib/jquery.js
orbited/static/demos/stomp/index.html
orbited/static/demos/stomp/shell.js
orbited/static/demos/stomp/style.css
orbited/static/demos/telnet/index.html
orbited/static/demos/telnet/telnet-gui.js
orbited/static/demos/websocket/index.html
orbited/static/demos/xmpp/background.png
orbited/static/demos/xmpp/buddy.png
orbited/static/demos/xmpp/chat.js
orbited/static/demos/xmpp/index.html
orbited/static/demos/xmpp/userlist.js
orbited/static/demos/xmpp/xmpp.css
orbited/static/demos/xmpp/xmpp.js
orbited/static/protocols/irc/irc2.js
orbited/static/protocols/stomp/stomp.js
orbited/static/protocols/telnet/telnet.js
orbited/static/protocols/xmpp/xmpp.js
orbited/static/tests/orbited.html
orbited/static/tests/tcpsocket.html
orbited/static/tests/utf8.html
orbited/static/tests/lib/doh/Makefile
orbited/static/tests/lib/doh/doh.js
orbited/static/tests/lib/doh/orbited.profile.js
orbited/static/tests/lib/doh/_firebug/LICENSE
orbited/static/tests/lib/doh/_firebug/errorIcon.png
orbited/static/tests/lib/doh/_firebug/firebug.css
orbited/static/tests/lib/doh/_firebug/infoIcon.png
orbited/static/tests/lib/doh/_firebug/tab_lft_norm.png
