Metadata-Version: 1.0
Name: orbited
Version: 0.7.8
Summary: A browser(javascript)->tcp bridge; Comet is used to emulate TCP connections in the browser; Allows you to connect a web browser directly to an IRC or XMPP server, for instance.
Home-page: http://www.orbited.org
Author: Michael Carter
Author-email: CarterMichael@gmail.com
License: MIT License
Download-URL: http://www.orbited.org/download
Platform: UNKNOWN
Classifier: Development Status :: 4 - Beta
Classifier: Environment :: Console
Classifier: Intended Audience :: Developers
Classifier: License :: OSI Approved :: MIT License
Classifier: Operating System :: OS Independent
Classifier: Programming Language :: Python
Classifier: Topic :: Software Development :: Libraries :: Python Modules
